{
  "data": [
    {
      "id": "1",
      "name": "narayan",
      "sname": "singh",
      "email": "nar@gmail.com",
      "quali": "engineer ",
      "password": "123"
    },
    {
      "id": "2",
      "name": "prajwal",
      "sname": "singh",
      "email": "pr@gmail.com",
      "quali": "doctor ",
      "password": "1233"
    },
    {
      "id": "3",
      "name": "ujjwal",
      "sname": "singh",
      "email": "ujj@gmail.com",
      "quali": "accountant ",
      "password": "1234"
    },
    {
      "id": "4",
      "name": "aman",
      "sname": "singh",
      "email": "am@gmail.com",
      "quali": "engineer",
      "password": "1235"
    },
    {
      "name": "vishesh",
      "lastName": "Mathur",
      "email": "Mathur@gmail.com",
      "quali": "engineer",
      "id": "41xxSiG",
      "password": "1236"
    },
    {
      "name": "raghav",
      "lastName": "prabhu ji",
      "email": "rp@gmail.com",
      "quali": "engineer",
      "id": "9pgQPWX",
      "password": "1237"
    },
    {
      "fname": "bb",
      "lname": "b",
      "email": "b@gmail.com",
      "quali": "js",
      "password": "jjj",
      "id": "PcbHMnN"
    },
    {
      "fname": "bb",
      "lname": "b",
      "email": "b@gmail.com",
      "quali": "js",
      "password": "jjj",
      "id": "EOGcPev"
    }
  ]
}